typing_ex-0.1.32.dist-info/METADATA
typing_ex-0.1.32.dist-info/WHEEL
typing_ex-0.1.32.dist-info/licenses/LICENSE
typing_ex/__init__.py
typing_ex/builtin_typing.py
typing_ex/enum_ex.py
typing_ex/experimental.py
typing_ex/frozen.py
typing_ex/type_info.py
typing_ex/typed_defaultdict.py
typing_ex-0.1.32.dist-info/RECORD
