Metadata-Version: 2.1
Name: typing_ex
Version: 0.1.32
Summary: A package for extended built-in types
Author-Email: yusing <yusing.wys@gmail.com>
License: MIT
Requires-Python: >=3.8
Requires-Dist: typing-extensions>=4.9.0
Requires-Dist: isort>=5.13.2; extra == "dev"
Requires-Dist: black>=24.2.0; extra == "dev"
Requires-Dist: flakehell>=0.9.0; extra == "dev"
Requires-Dist: flake8-bugbear>=23.3.12; extra == "dev"
Requires-Dist: flake8-mypy>=17.8.0; extra == "dev"
Requires-Dist: flake8-builtins>=2.2.0; extra == "dev"
Requires-Dist: coverage>=7.4.1; extra == "dev"
Requires-Dist: mypy>=1.8.0; extra == "dev"
Requires-Dist: pytest>=8.0.1; extra == "test"
Provides-Extra: dev
Provides-Extra: test
